antennex_client/__init__.py
antennex_client/api/__init__.py
antennex_client/api/antennex_api.py
antennex_client/api/default_api.py
antennex_client/api_client.py
antennex_client/api_response.py
antennex_client/configuration.py
antennex_client/examples/01_connect_and_get_status/get_status.py
antennex_client/examples/02_start_measurement/antenna_efficiency_reciprocal_measurement.py
antennex_client/examples/02_start_measurement/antenna_efficiency_transmitter_measurement.py
antennex_client/examples/02_start_measurement/get_data_available.py
antennex_client/examples/02_start_measurement/oscilloscope_fmcw_measurement.py
antennex_client/examples/02_start_measurement/sa_chamber_calibration.py
antennex_client/examples/02_start_measurement/spectrum_measurement.py
antennex_client/examples/02_start_measurement/vna_chamber_calibration.py
antennex_client/examples/02_start_measurement/zero_span_measurement.py
antennex_client/examples/03_set_user_calibration_files/set_antenna_efficiency.py
antennex_client/examples/03_set_user_calibration_files/set_external_calibration_file.py
antennex_client/examples/03_set_user_calibration_files/show_current_calibration_file.py
antennex_client/examples/04_get_and_test_settings/change_settings.py
antennex_client/examples/05_change_device_preset/change_device_preset.py
antennex_client/examples/06_basic_chamber_hardware_control/basic_chamber_hardware_control.py
antennex_client/examples/hostname.txt
antennex_client/exceptions.py
antennex_client/functions.py
antennex_client/models/__init__.py
antennex_client/models/acquire_frequency_range.py
antennex_client/models/acquisition_mode.py
antennex_client/models/acquisition_progress.py
antennex_client/models/acquisition_types.py
antennex_client/models/antenna_efficiency_settings.py
antennex_client/models/axis_description.py
antennex_client/models/component_operational_state.py
antennex_client/models/data2d_types.py
antennex_client/models/data_types.py
antennex_client/models/device_address.py
antennex_client-3.4.0.dist-info/LICENSE
antennex_client-3.4.0.dist-info/METADATA
antennex_client-3.4.0.dist-info/WHEEL
antennex_client-3.4.0.dist-info/RECORD
